Metadata-Version: 1.0
Name: harrytsz
Version: 0.1
Summary: harrytsz magic toolbox
Home-page: http://github.com/harrytsz/harrytsz
Author: Harrytsz
Author-email: taosizhan@gmail.com
License: MIT
Platform: UNKNOWN
